MANIFEST.in
README.md
pypi.rst
setup.py
hashcrack/__init__.py
hashcrack/add.py
hashcrack/cli.py
hashcrack/common.py
hashcrack/config.py
hashcrack/crack.py
hashcrack/help.py
hashcrack/identify.py
hashcrack/john.py
hashcrack/set.py
hashcrack/show.py
hashcrack/types.py
hashcrack/version.py
hashcrack/autoconfig/7z2hashcat
hashcrack/autoconfig/7z2hashcat.exe.xz
hashcrack/autoconfig/7z2hashcat.pl
hashcrack/autoconfig/__init__.py
hashcrack/autoconfig/john_build_notes.txt
hashcrack/autoconfig/pcap.py
hashcrack/autoconfig/rar.py
hashcrack/autoconfig/seven_zip.py
hashcrack/autoconfig/shadow.py
hashcrack/autoconfig/zip.py
hashcrack/static/john.exe.tar.xz
hashcrack/static/john.xz
hashcrack/static/kwp/basechars/ascii.base
hashcrack/static/kwp/basechars/full.base
hashcrack/static/kwp/basechars/tiny.base
hashcrack/static/kwp/keymaps/de.keymap
hashcrack/static/kwp/keymaps/en.keymap
hashcrack/static/kwp/keymaps/es.keymap
hashcrack/static/kwp/keymaps/fr.keymap
hashcrack/static/kwp/keymaps/ru.keymap
hashcrack/static/kwp/keymaps/sv.keymap
hashcrack/static/kwp/routes/2-to-10-max-2-direction-changes-combinator.route
hashcrack/static/kwp/routes/2-to-10-max-3-direction-changes.route
hashcrack/static/kwp/routes/2-to-16-max-3-direction-changes.route
hashcrack/static/kwp/routes/2-to-16-max-4-direction-changes.route
hashcrack/static/kwp/routes/2-to-32-max-5-direction-changes.route
hashcrack/static/kwp/routes/2-to-4-exhaustive-prince.route
hashcrack/static/kwp/routes/4-to-4-exhaustive.route
hashcrack/static/rules/Incisive-leetspeak.rule
hashcrack/static/rules/InsidePro-HashManager.rule
hashcrack/static/rules/InsidePro-PasswordsPro.rule
hashcrack/static/rules/OneRuleToRuleThemAll.rule
hashcrack/static/rules/T0XlC-insert_00-99_1950-2050_toprules_0_F.rule
hashcrack/static/rules/T0XlC-insert_space_and_special_0_F.rule
hashcrack/static/rules/T0XlC-insert_top_100_passwords_1_G.rule
hashcrack/static/rules/T0XlC.rule
hashcrack/static/rules/T0XlCv1.rule
hashcrack/static/rules/best64.rule
