Metadata-Version: 2.1
Name: hashcrack
Version: 0.9
Summary: Menu for cracking hashes.
Home-page: https://github.com/bannsec/hashcrack
Author: Michael Bann
Author-email: self@bannsecurity.com
License: MIT
Keywords: password hashcat cracking
Platform: UNKNOWN
Classifier: Development Status :: 3 - Alpha
Classifier: Intended Audience :: End Users/Desktop
Classifier: License :: OSI Approved :: MIT License
Classifier: Programming Language :: Python :: 3
Classifier: Operating System :: POSIX :: Linux
Classifier: Environment :: Console
Provides-Extra: dev
